mixport/__init__.py
mixport/__main__.py
mixport/transcode.py
mixport-0.1.0.dist-info/LICENSE
mixport-0.1.0.dist-info/METADATA
mixport-0.1.0.dist-info/WHEEL
mixport-0.1.0.dist-info/entry_points.txt
mixport-0.1.0.dist-info/top_level.txt
mixport-0.1.0.dist-info/RECORD
